src/__init__.py
src/downloader/__init__.py
src/downloader/downloader.py
src/tests/__init__.py
src/tests/conftest.py
src/tests/test_downloader.py
mapbiomas_downloader-2.2.0.dist-info/LICENSE
mapbiomas_downloader-2.2.0.dist-info/METADATA
mapbiomas_downloader-2.2.0.dist-info/WHEEL
mapbiomas_downloader-2.2.0.dist-info/RECORD
