Metadata-Version: 2.3
Name: mapbiomas-downloader
Version: 2.2.0
Summary: Ferramenta para download de arquivos GeoTIFF do MapBiomas para municípios ou estados brasileiros
License: MIT
Author: Ricardo Malnati
Requires-Python: >=3.12
Classifier: License :: OSI Approved :: MIT License
Classifier: Programming Language :: Python :: 3
Classifier: Programming Language :: Python :: 3.12
Classifier: Programming Language :: Python :: 3.13
Requires-Dist: aiohttp (>=3.8.0)
Requires-Dist: geopandas (>=0.14.0)
Requires-Dist: importlib-resources (>=5.12.0)
Requires-Dist: pandas (>=2.0.0)
Requires-Dist: playwright (>=1.40.0)
Requires-Dist: rasterio (>=1.3.7)
Project-URL: Repository, https://github.com/malnati/mapbiomas-downloader
